purr_petra_cli/__init__.py
purr_petra_cli/asset.py
purr_petra_cli/cli.py
purr_petra_cli/dbisam.py
purr_petra_cli/epsg.py
purr_petra_cli/post_process.py
purr_petra_cli/proj.py
purr_petra_cli/setup.py
purr_petra_cli/util.py
purr_petra_cli/xformer.py
purr_petra_cli/recipes/__init__.py
purr_petra_cli/recipes/core.py
purr_petra_cli/recipes/dst.py
purr_petra_cli/recipes/formation.py
purr_petra_cli/recipes/ip.py
purr_petra_cli/recipes/perforation.py
purr_petra_cli/recipes/production.py
purr_petra_cli/recipes/raster_log.py
purr_petra_cli/recipes/survey.py
purr_petra_cli/recipes/vector_log.py
purr_petra_cli/recipes/well.py
purr_petra_cli/recipes/zone.py
purr_petra_cli-0.1.0.dist-info/licenses/LICENSE
purr_petra_cli-0.1.0.dist-info/METADATA
purr_petra_cli-0.1.0.dist-info/WHEEL
purr_petra_cli-0.1.0.dist-info/entry_points.txt
purr_petra_cli-0.1.0.dist-info/top_level.txt
purr_petra_cli-0.1.0.dist-info/RECORD
