Metadata-Version: 2.4
Name: purr-petra-cli
Version: 0.1.0
Summary: Add your description here
Requires-Python: >=3.13
License-File: LICENSE
Requires-Dist: numpy>=2.3.1
Requires-Dist: pandas>=2.3.0
Requires-Dist: psutil>=7.0.0
Requires-Dist: pyodbc>=5.2.0
Requires-Dist: typer>=0.16.0
Dynamic: license-file
